pixi/__init__.py
pixi/__main__.py
pixi/client.py
pixi/commands.py
pixi/config.py
pixi/database.py
pixi/errors.py
pixi/migrations/0001.sql
pixi/options.py
pixi/util.py
pixi-1.0.1.dist-info/entry_points.txt
pixi-1.0.1.dist-info/LICENSE
pixi-1.0.1.dist-info/WHEEL
pixi-1.0.1.dist-info/METADATA
pixi-1.0.1.dist-info/RECORD
