Metadata-Version: 2.1
Name: pixi
Version: 1.0.1
Summary: A command line tool to download images from Pixiv.
Home-page: https://github.com/azuline/pixi
License: Apache-2.0
Author: azuline
Author-email: azuline@riseup.net
Requires-Python: >=3.7,<4.0
Classifier: License :: OSI Approved :: Apache Software License
Classifier: Programming Language :: Python :: 3
Classifier: Programming Language :: Python :: 3.7
Classifier: Programming Language :: Python :: 3.8
Requires-Dist: appdirs (>=1.4,<2.0)
Requires-Dist: click (>=7.0,<8.0)
Requires-Dist: pixiv-api (>=0.3.0,<0.4.0)
Requires-Dist: tqdm (>=4.32,<5.0)
Project-URL: Repository, https://github.com/azuline/pixi
